[
    {
        "title":  "LỜI CẢM ƠN",
        "author":  "Admin",
        "date":  "07-12-2025",
        "thumbnail":  "https://hoitramhuongvietnam.org/images/thư_cảm_ơn_hội_viên_ủng_hộ_đồng_bào_bị_thiệt_hại_do_bảo_lũ_ở_miền_trung_đã_ký-hình_ảnh-0.jpg",
        "link":  "https://hoitramhuongvietnam.org/bang-tin-hoi/loi-cam-on-chung-tay-ho-tro-dong-bao-mien-trung-tay-nguyen-khac-phuc-bao-lu.html"
    },
    {
        "title":  "THÔNG BÁO",
        "author":  "Admin",
        "date":  "02-12-2025",
        "thumbnail":  "https://hoitramhuongvietnam.org/images/125.jpg",
        "link":  "https://hoitramhuongvietnam.org/bang-tin-hoi/thong-bao-ve-viec-uy-vien-bch-va-hoi-vien-cung-cap-thong-tin-ca-nhan.html"
    },
    {
        "title":  "QUYẾT ĐỊNH - Thành lập Ban Nghiên cứu và Phát triển Trầm hương trực thuộc Hội Trầm hương Việt Nam",
        "author":  "Admin",
        "date":  "16-08-2025",
        "thumbnail":  "https://hoitramhuongvietnam.org/images/1-hht.jpg",
        "link":  "https://hoitramhuongvietnam.org/bang-tin-hoi/quyet-dinh-thanh-lap-ban-nghien-cuu-va-phat-trien-tram-huong.html"
    },
    {
        "title":  "CHỦ TỊCH HỘI TRẦM HƯƠNG VIỆT NAM (VAWA) PHẠM VĂN DU CHÚC MỪNG NĂM MỚI XUÂN ẤT TỴ - 2025",
        "author":  "Admin",
        "date":  "28-01-2025",
        "thumbnail":  "https://hoitramhuongvietnam.org/images/thieptet2025-1(1).png",
        "link":  "https://hoitramhuongvietnam.org/bang-tin-hoi/thu-chuc-tet-cua-chu-tich-hoi-tram-huong.html"
    },
    {
        "title":  "Thông báo về việc tham gia hội chợ Dược liệu, Y Dược cổ truyền và các sản phẩm từ dược liệu",
        "author":  "Admin",
        "date":  "18-10-2024",
        "thumbnail":  "https://hoitramhuongvietnam.org/images/tv_brochure___vietramed_expo__2024_final_prv-0.jpg",
        "link":  "https://hoitramhuongvietnam.org/bang-tin-hoi/thong-bao-tham-gia-hoi-cho-duoc-lieu.html"
    },
    {
        "title":  "LỜI CẢM ƠN",
        "author":  "Admin",
        "date":  "03-10-2024",
        "thumbnail":  "https://hoitramhuongvietnam.org/images/06a6831128a98ef7d7b8.jpg",
        "link":  "https://hoitramhuongvietnam.org/bang-tin-hoi/loi-cam-on-ve-viec-ung-ho-dong-bao-mien-bac.html"
    },
    {
        "title":  "Thông báo danh sách hội viên nộp quỹ hội năm 2024",
        "author":  "Admin",
        "date":  "02-10-2024",
        "thumbnail":  "https://hoitramhuongvietnam.org/images/2d75885212eab4b4edfb.jpg",
        "link":  "https://hoitramhuongvietnam.org/bang-tin-hoi/danh-sach-hoi-vien-nop-quy-hoi.html"
    },
    {
        "title":  "THƯ KÊU GỌI",
        "author":  "Admin",
        "date":  "16-09-2024",
        "thumbnail":  "https://hoitramhuongvietnam.org/images/f5fdf6ace7f741a918e6.jpg",
        "link":  "https://hoitramhuongvietnam.org/bang-tin-hoi/thu-keu-goi.html"
    },
    {
        "title":  "Danh sách hội viên Hội Trầm hương Việt Nam được cấp Thẻ hội viên kỳ hạn 2024-2028",
        "author":  "Admin",
        "date":  "13-08-2024",
        "thumbnail":  "https://hoitramhuongvietnam.org/images/144464f2dee67ab823f7.jpg",
        "link":  "https://hoitramhuongvietnam.org/bang-tin-hoi/danh-sach-hoi-vien-duoc-cap-the.html"
    },
    {
        "title":  "THÔNG BÁO HỘI VIÊN ĐÓNG HỘI PHÍ NĂM 2024",
        "author":  "Admin",
        "date":  "12-08-2024",
        "thumbnail":  "https://hoitramhuongvietnam.org/images/8f8479c8c2dc66823fcd.jpg",
        "link":  "https://hoitramhuongvietnam.org/bang-tin-hoi/thong-bao-hoi-vien-dong-hoi-phi-nam-2024.html"
    },
    {
        "title":  "THÔNG BÁO THẺ HỘI VIÊN HẾT HẠN SỬ DỤNG",
        "author":  "Admin",
        "date":  "12-08-2024",
        "thumbnail":  "https://hoitramhuongvietnam.org/images/9d7ccb3b702fd4718d3e.jpg",
        "link":  "https://hoitramhuongvietnam.org/bang-tin-hoi/thong-bao-the-hoi-vien-het-han-su-dung.html"
    },
    {
        "title":  "Quyết định về việc công bố mẫu thẻ hội viên Hội Trầm hương Việt Nam kỳ hạn 2024-2028",
        "author":  "Admin",
        "date":  "12-08-2024",
        "thumbnail":  "https://hoitramhuongvietnam.org/images/d9bbe0fd5be9ffb7a6f8.jpg",
        "link":  "https://hoitramhuongvietnam.org/bang-tin-hoi/cong-bo-mau-the-hoi-vien-ky-han-2024-2028.html"
    },
    {
        "title":  "Quy chế quản lý và sử dụng thẻ hội viên Hội Trầm hương Việt Nam kỳ hạn 2024-2028",
        "author":  "Admin",
        "date":  "12-08-2024",
        "thumbnail":  "https://hoitramhuongvietnam.org/images/f6fd85443f509b0ec241.jpg",
        "link":  "https://hoitramhuongvietnam.org/bang-tin-hoi/ban-hanh-quy-che-quan-ly-va-su-dung-the-hoi-vien.html"
    },
    {
        "title":  "THƯ CHÚC MỪNG NĂM MỚI. XUÂN GIÁP THÌN - 2024",
        "author":  "Admin",
        "date":  "10-02-2024",
        "thumbnail":  "https://hoitramhuongvietnam.org/images/banner-thiep-tet-2024.jpg",
        "link":  "https://hoitramhuongvietnam.org/bang-tin-hoi/thu-chuc-mung-nam-moi.html"
    },
    {
        "title":  "Kính gửi: Ban Chấp hành và Hội viên Hội Trầm hương Việt Nam.",
        "author":  "Admin",
        "date":  "11-01-2024",
        "thumbnail":  "https://hoitramhuongvietnam.org/images/thong_bao.jpg",
        "link":  "https://hoitramhuongvietnam.org/bang-tin-hoi/cap-nhat-noi-dung-dieu-le-hoi-tram-huong-viet-nam.html"
    },
    {
        "title":  "Link tham gia chương trình thực nghiệm cấy tạo Trầm hương trên cây Dó bầu tại Bình Phước trong 5 năm (2023 - 2028)",
        "author":  "Admin",
        "date":  "08-08-2023",
        "thumbnail":  "https://hoitramhuongvietnam.org/images/thbao-hth.jpg",
        "link":  "https://hoitramhuongvietnam.org/bang-tin-hoi/thuc-nghiem-cay-tao-tram-huong-tren-cay-do-bau-tai-binh-phuoc.html"
    },
    {
        "title":  "Thực nghiệm cấy tạo Trầm hương trên cây Dó bầu tại Bình Phước trong 5 năm (2023 - 2028)",
        "author":  "Admin",
        "date":  "08-08-2023",
        "thumbnail":  "https://hoitramhuongvietnam.org/images/thbao-hth(1).jpg",
        "link":  "https://hoitramhuongvietnam.org/bang-tin-hoi/thuc-nghiem-cay-tao-tram-huong-tren-cay-do-bau-tai-binh-phuoc-trong-5-nam-2023-2028.html"
    },
    {
        "title":  "Triển vọng xuất khẩu Trầm hương Việt Nam sang thị trường Trung Quốc và Trung Đông bằng thương mại điện tử",
        "author":  "Admin",
        "date":  "31-07-2023",
        "thumbnail":  "https://hoitramhuongvietnam.org/images/logo-hth.png",
        "link":  "https://hoitramhuongvietnam.org/bang-tin-hoi/trien-vong-xuat-khau-tram-huong-viet-nam-sang-thi-truong-trung-quoc-va-trung-dong.html"
    },
    {
        "title":  "Đại hội lần III nhiệm kỳ 2023 - 2028 Hội Trầm hương Việt Nam: Nỗ lực nâng cao hiệu quả, sức cạnh tranh cho loài cây quý",
        "author":  "Admin",
        "date":  "16-05-2023",
        "thumbnail":  "https://hoitramhuongvietnam.org/images/1-1684066186.jpg",
        "link":  "https://hoitramhuongvietnam.org/bang-tin-hoi/dai-hoi-lan-iii-nhiem-ky-2023-2028.html"
    },
    {
        "title":  "Hội Trầm hương Việt Nam tổ chức thành công đại hội nhiệm kỳ III (2023 – 2028)",
        "author":  "Admin",
        "date":  "15-05-2023",
        "thumbnail":  "https://hoitramhuongvietnam.org/images/2-1684066225.jpg",
        "link":  "https://hoitramhuongvietnam.org/bang-tin-hoi/hoi-tram-huong-viet-nam-to-chuc-thanh-cong-dai-hoi-nhiem-ky-3.html"
    },
    {
        "title":  "Tổ chức thành công đại hội nhiệm kỳ III (2023 – 2028) Hội Trầm hương Việt Nam",
        "author":  "Admin",
        "date":  "15-05-2023",
        "thumbnail":  "https://hoitramhuongvietnam.org/images/6-1684066610.jpg",
        "link":  "https://hoitramhuongvietnam.org/bang-tin-hoi/to-chuc-thanh-cong-dai-hoi-nhiem-ky-3-hoi-tram-huong-viet-nam.html"
    },
    {
        "title":  "Thư mời tham dự Đại Hội Hội Trầm Hương Việt Nam nhiệm kỳ 3",
        "author":  "Admin",
        "date":  "03-05-2023",
        "thumbnail":  "https://hoitramhuongvietnam.org/images/thumoi_Đhth_1.jpg",
        "link":  "https://hoitramhuongvietnam.org/bang-tin-hoi/thu-moi-tham-du-dai-hoi-lan-3.html"
    },
    {
        "title":  "Hội trầm hương Việt Nam tham dự lễ giỗ tổ ngành trầm hương, thăm và làm việc với hội trầm hương tỉnh Khánh Hoà",
        "author":  "Admin",
        "date":  "06-04-2022",
        "thumbnail":  "https://hoitramhuongvietnam.org/images/5f23fd98b58f7bd1229e3.jpg",
        "link":  "https://hoitramhuongvietnam.org/bang-tin-hoi/hoi-tram-huong-tham-gia-le-gio-to-nganh-tram-huong.html"
    },
    {
        "title":  "CẢNH BÁO",
        "author":  "Admin",
        "date":  "30-05-2021",
        "thumbnail":  "https://hoitramhuongvietnam.org/images/canhbao.jpg",
        "link":  "https://hoitramhuongvietnam.org/bang-tin-hoi/canh-bao-ve-viec-dau-tu-tram-huong.html"
    },
    {
        "title":  "Thư báo mời họp",
        "author":  "Admin",
        "date":  "31-03-2021",
        "thumbnail":  "https://hoitramhuongvietnam.org/images/thongbaomoiduhop.jpg",
        "link":  "https://hoitramhuongvietnam.org/bang-tin-hoi/thong-bao-hop-toa-dam.html"
    },
    {
        "title":  "Thư Mời Họp Thường Trực Mở Rộng Cuối Năm Của Ban Chấp Hành Hội Trầm Hương Việt Nam",
        "author":  "Admin",
        "date":  "04-01-2021",
        "thumbnail":  "https://hoitramhuongvietnam.org/images/thbao(1).jpg",
        "link":  "https://hoitramhuongvietnam.org/bang-tin-hoi/thu-moi-hop-thuong-truc-mo-rong-cuoi-nam.html"
    },
    {
        "title":  "Báo cáo hoạt động 6 tháng đầu năm 2018 và kế hoạch triển khai 6 tháng cuối năm",
        "author":  "Admin",
        "date":  "24-11-2018",
        "thumbnail":  "https://hoitramhuongvietnam.org/images/baoca.jpg",
        "link":  "https://hoitramhuongvietnam.org/bang-tin-hoi/bao-cao-hoat-dong-6-thang-dau-nam-2018-va-ke-hoach-trien-khai-6-thang-cuoi-nam.html"
    },
    {
        "title":  "Bảng phân công nhiệm vụ ủy viên ban thường trực và ban chấp hành, nhiệm kỳ 2015-2020",
        "author":  "Admin",
        "date":  "18-11-2018",
        "thumbnail":  "https://hoitramhuongvietnam.org/images/clip_image002(1).png",
        "link":  "https://hoitramhuongvietnam.org/bang-tin-hoi/bang-phan-cong-nhiem-vu-uy-vien-ban-thuong-truc-va-ban-chap-hanhnhiem-ky-2015-2020.html"
    },
    {
        "title":  "Tháng 4/2018 - BCH Hội Trầm Hương thông báo tiến hành đặt thẻ hội viên mới",
        "author":  "Admin",
        "date":  "11-11-2018",
        "thumbnail":  "https://hoitramhuongvietnam.org/images/thehoven.jpg",
        "link":  "https://hoitramhuongvietnam.org/bang-tin-hoi/thang-4-2018-bch-hoi-tram-huong-thong-bao-tien-hanh-dat-the-hoi-vien-moi.html"
    },
    {
        "title":  "Thông báo Chương trình: Hội nghị tổng kết 2016 và phương hướng hoạt động 2017",
        "author":  "Admin",
        "date":  "03-01-2017",
        "thumbnail":  "https://hoitramhuongvietnam.org/images/thongbao.jpg",
        "link":  "https://hoitramhuongvietnam.org/bang-tin-hoi/thong-bao-chuong-trinhhoi-nghi-tong-ket-2016-va-phuong-huong-hoat-dong-2017.html"
    },
    {
        "title":  "BẢNG BÁO CÁO HOẠT ĐỘNG THÁNG 8/2016",
        "author":  "Admin",
        "date":  "20-09-2016",
        "thumbnail":  "https://hoitramhuongvietnam.org/images/baocao.jpg",
        "link":  "https://hoitramhuongvietnam.org/bang-tin-hoi/bang-bao-cao-hoat-dong-thang-8-2016.html"
    },
    {
        "title":  "Thư mời Hội thảo quốc tế",
        "author":  "Admin",
        "date":  "06-08-2016",
        "thumbnail":  "https://hoitramhuongvietnam.org/images/clip_image002.png",
        "link":  "https://hoitramhuongvietnam.org/bang-tin-hoi/thu-moi-hoi-thao-quoc-te.html"
    },
    {
        "title":  "Biên bản họp Ban thường trực Hội tháng 8-2016",
        "author":  "Admin",
        "date":  "06-08-2016",
        "thumbnail":  "https://hoitramhuongvietnam.org/images/clip_image00123.png",
        "link":  "https://hoitramhuongvietnam.org/bang-tin-hoi/bien-ban-hop-ban-thuong-truc-hoi-thang-8-2016.html"
    },
    {
        "title":  "BÁO CÁO TÌNH HÌNH HOẠT ĐỘNG 6 THÀNG ĐẦU NĂM 2016  VÀ PHƯƠNG HƯỚNG HOẠT ĐỘNG 6 THÁNG CUỐI NĂM 2016",
        "author":  "Admin",
        "date":  "25-07-2016",
        "thumbnail":  "https://hoitramhuongvietnam.org/images/report3.jpg",
        "link":  "https://hoitramhuongvietnam.org/bang-tin-hoi/bao-cao-tinh-hinh-hoat-dong-6-thang-dau-nam-2016-va-phuong-huong-hoat-dong-6-thang-cuoi-nam-2016.html"
    },
    {
        "title":  "THÔNG BÁO SỐ 1 “ Về việc tổ chức Hội thảo Khoa học lần thứ I”",
        "author":  "Admin",
        "date":  "15-07-2016",
        "thumbnail":  "https://hoitramhuongvietnam.org/images/thong_bao(1).jpg",
        "link":  "https://hoitramhuongvietnam.org/bang-tin-hoi/thong-bao-so-1-.html"
    },
    {
        "title":  "HỘI TRẦM HƯƠNG VIỆT NAM THÔNG BÁO",
        "author":  "Admin",
        "date":  "06-06-2016",
        "thumbnail":  "https://hoitramhuongvietnam.org/images/thong_bao.jpg",
        "link":  "https://hoitramhuongvietnam.org/bang-tin-hoi/hoi-tram-huong-viet-nam-thong-bao.html"
    },
    {
        "title":  "Nghị quyết đại hội Hội trầm hương việt nam Nhiệm kỳ 2: 2015 – 2020",
        "author":  "Admin",
        "date":  "20-05-2016",
        "thumbnail":  "https://hoitramhuongvietnam.org/images/logo.jpg",
        "link":  "https://hoitramhuongvietnam.org/bang-tin-hoi/nghi-quyet-dai-hoi-hoi-tram-huong-viet-nam-nhiem-ky-22015-.html"
    },
    {
        "title":  "Báo cáo của ban kiểm tra, Nhiệm kỳ 2010-2015",
        "author":  "Admin",
        "date":  "19-05-2016",
        "thumbnail":  "https://hoitramhuongvietnam.org/images/logo.jpg",
        "link":  "https://hoitramhuongvietnam.org/bang-tin-hoi/bao-cao-cua-ban-kiem-tranhiem-ky-2010-2015.html"
    },
    {
        "title":  "Báo cáo Tổng kết tình hình hoạt động nhiệm kỳ 1 và Phương hướng hoạt động Nhiệm kỳ 2 (2015-2020)",
        "author":  "Admin",
        "date":  "18-05-2016",
        "thumbnail":  "https://hoitramhuongvietnam.org/images/logo.jpg",
        "link":  "https://hoitramhuongvietnam.org/bang-tin-hoi/bao-cao-tong-ket-tinh-hinh-hoat-dong-nhiem-ky-1-va-phuong-huong-hoat-dong-nhiem-ky-2-(2015-2020).html"
    },
    {
        "title":  "Báo Cáo Thực Trạng Định Hướng Phát Triển  Loài Cây Dó Bầu Và Trầm Hương  Trên Thị Trường Hà Tĩnh",
        "author":  "Admin",
        "date":  "08-04-2016",
        "thumbnail":  "https://hoitramhuongvietnam.org/images/agio-tram-ky-anh-1234.jpg",
        "link":  "https://hoitramhuongvietnam.org/bang-tin-hoi/bao-cao-thuc-trang-dinh-huong-phat-trien-loai-cay-do-bau-va-tram-huong-tren-thi-truong-ha-tinh.html"
    },
    {
        "title":  "Làm việc với trường Đại học Lâm nghiệp về Nghị định thư của Đức về Trầm hương",
        "author":  "Admin",
        "date":  "01-04-2016",
        "thumbnail":  "https://hoitramhuongvietnam.org/images/clip_image002_00011.jpg",
        "link":  "https://hoitramhuongvietnam.org/bang-tin-hoi/lam-viec-voi-truong-dai-hoc-lam-nghiep-ve-nghi-dinh-thu-cua-duc-ve-tram-huong.html"
    },
    {
        "title":  "Làm việc cùng Chi hội Trầm hương tỉnh Khánh Hòa",
        "author":  "Admin",
        "date":  "01-04-2016",
        "thumbnail":  "https://hoitramhuongvietnam.org/images/clip_image008_0001(1).jpg",
        "link":  "https://hoitramhuongvietnam.org/bang-tin-hoi/lam-viec-cung-chi-hoi-tram-huong-tinh-khanh-hoa.html"
    },
    {
        "title":  "Làm việc với các Hội viên Trầm hương phía Bắc",
        "author":  "Admin",
        "date":  "31-03-2016",
        "thumbnail":  "https://hoitramhuongvietnam.org/images/clip0056.jpg",
        "link":  "https://hoitramhuongvietnam.org/bang-tin-hoi/lam-viec-voi-cac-hoi-vien-tram-huong-phia-bac.html"
    },
    {
        "title":  "Làm việc với Sở Nông nghiệp và PTNT tỉnh Hà Tĩnh",
        "author":  "Admin",
        "date":  "31-03-2016",
        "thumbnail":  "https://hoitramhuongvietnam.org/images/clip_image004_0000(1).jpg",
        "link":  "https://hoitramhuongvietnam.org/bang-tin-hoi/lam-viec-voi-so-nong-nghiep-va-ptnt-tinh-ha-tinh.html"
    },
    {
        "title":  "Báo cáo tình hình hoạt động năm 2015 và phương hướng hoạt động năm 2016",
        "author":  "Admin",
        "date":  "22-12-2015",
        "thumbnail":  "https://hoitramhuongvietnam.org/images/1500usd_1.jpg",
        "link":  "https://hoitramhuongvietnam.org/bang-tin-hoi/bao-cao-tinh-hinh-hoat-dong-nam-2015-va-phuong-huong-hoat-dong-nam-2016.html"
    },
    {
        "title":  "Bảng tổng hợp báo cáo hoạt động đối ngoại 2015",
        "author":  "Admin",
        "date":  "21-12-2015",
        "thumbnail":  "https://hoitramhuongvietnam.org/images/logo(2).jpg",
        "link":  "https://hoitramhuongvietnam.org/bang-tin-hoi/bang-tong-hop-bao-cao-hoat-dong-doi-ngoai-2015.html"
    },
    {
        "title":  "Biên bản hội nghị giữa sở nông nghiệp \u0026 PTNN Hà Tĩnh với Hội Trầm Hương Việt Nam",
        "author":  "Admin",
        "date":  "21-12-2015",
        "thumbnail":  "https://hoitramhuongvietnam.org/images/logo(3).jpg",
        "link":  "https://hoitramhuongvietnam.org/bang-tin-hoi/bien-ban-hoi-nghi-giua-so-nong-nghiep-ptnn-ha-tinh-voi-hoi-tram-huong-viet-nam.html"
    },
    {
        "title":  "Báo cáo công tác đối ngoại năm 2015 và phương hướng công tác năm 2016",
        "author":  "Admin",
        "date":  "21-12-2015",
        "thumbnail":  "https://hoitramhuongvietnam.org/images/logo(4).jpg",
        "link":  "https://hoitramhuongvietnam.org/bang-tin-hoi/bao-cao-cong-tac-doi-ngoai-nam-2015-va-phuong-huong-cong-tac-nam-2016.html"
    }
]
